vp9dash/__init__.py
vp9dash/wrapper.py
vp9dash-0.0.1.dist-info/DESCRIPTION.rst
vp9dash-0.0.1.dist-info/entry_points.txt
vp9dash-0.0.1.dist-info/METADATA
vp9dash-0.0.1.dist-info/metadata.json
vp9dash-0.0.1.dist-info/RECORD
vp9dash-0.0.1.dist-info/top_level.txt
vp9dash-0.0.1.dist-info/WHEEL
