Metadata-Version: 2.0
Name: vp9dash
Version: 0.0.1
Summary: FFMpeg wrapper script to create VP9 MPEG-DASH packages
Home-page: https://github.com/Eyevinn/vp9-dash
Author: Jonas Birme
Author-email: jonas.birme@eyevinn.se
License: MIT
Platform: UNKNOWN
Requires-Dist: pycurl
